{
  "metadata": {
    "scenario_name": "Scénario de Référence",
    "export_date": "2025-08-13T19:10:04.709Z",
    "version": "2.2-corrige"
  },
  "parameters": {
    "id": "reference",
    "name": "Scénario de Référence",
    "description": "Basé sur Business Plan avec corrections et optimisations",
    "fixedCosts": {
      "rent": 4500,
      "insurance": 500,
      "electricity": 3400,
      "maintenance": 1000,
      "admin": 6500,
      "amortization": 1750
    },
    "payroll": {
      "year1": {
        "direction": 60000,
        "production": 150000,
        "commercial": 50000,
        "admin": 33000
      },
      "year2": {
        "direction": 65000,
        "production": 240000,
        "commercial": 80000,
        "admin": 63000
      },
      "year3": {
        "direction": 70000,
        "production": 480000,
        "commercial": 150000,
        "admin": 167000
      }
    },
    "ingredients": {
      "farine_boulangere": 0.78,
      "farine_peyi": 14,
      "levure": 6,
      "sel": 1,
      "emballage": 0.031,
      "livraison": 0.0156
    },
    "allocation": {
      "bi": 60,
      "pointchaud": 25,
      "legumerie": 10,
      "biscuiterie": 5
    },
    "production": {
      "launch_duration": 6,
      "launch_production": 37500,
      "cruise_production": 150000,
      "legumerie_prod_y1": 2250,
      "legumerie_growth": 18,
      "pointchaud_start": 8,
      "pointchaud_ca_init": 10000,
      "pointchaud_growth": 3,
      "biscuiterie_start": 21,
      "biscuiterie_prod": 3.75
    },
    "recipes": {
      "baguette_industrielle": {
        "farine_boulangere": 0.202,
        "levure": 0.003,
        "sel": 0.004,
        "prix_vente_moyen": 0.65
      },
      "legumerie": {
        "cout_matiere": 3.52,
        "prix_vente": 8.8
      },
      "pointchaud": {
        "taux_marge": 65
      },
      "biscuiterie": {
        "cout_matiere": 2.5,
        "prix_vente": 7
      }
    },
    "paymentTerms": {
      "clients": 30,
      "fournisseurs": 60
    }
  },
  "results": {
    "totalFixedCosts": 17650,
    "baguetteBreakEven": 25035,
    "legumerieBreakEven": 334,
    "pointchaudBreakEven": 6788,
    "globalBreakEven": 14,
    "monthlyTreasury": [
      {
        "month": 1, "periode": "Jan 2023", "year": 1, "monthInYear": 1, "ventes_mensuelles": 43050, "achats_mensuels": 15067.5, "encaissements_ventes": 0, "encaissements_exceptionnels": 1750000, "encaissements_total": 1750000, "decaissements_fournisseurs": 0, "decaissements_salaires": 0, "decaissements_charges_fixes": 17650, "decaissements_exceptionnels": 1750000, "decaissements_total": 1767650, "variation": -17650, "solde_cumule": 32350, "ligne_credit": 0, "creances_clients": 43050, "dettes_fournisseurs": 30135.0
      },
      {
        "month": 2, "periode": "Fév 2023", "year": 1, "monthInYear": 2, "ventes_mensuelles": 43347, "achats_mensuels": 15171.45, "encaissements_ventes": 0, "encaissements_exceptionnels": 0, "encaissements_total": 0, "decaissements_fournisseurs": 0, "decaissements_salaires": 0, "decaissements_charges_fixes": 17650, "decaissements_exceptionnels": 0, "decaissements_total": 17650, "variation": -17650, "solde_cumule": 14700, "ligne_credit": 0, "creances_clients": 43347, "dettes_fournisseurs": 30342.9
      },
      {
        "month": 3, "periode": "Mar 2023", "year": 1, "monthInYear": 3, "ventes_mensuelles": 43648.46, "achats_mensuels": 15276.96, "encaissements_ventes": 43050, "encaissements_exceptionnels": 0, "encaissements_total": 43050, "decaissements_fournisseurs": 15276.96, "decaissements_salaires": 0, "decaissements_charges_fixes": 17650, "decaissements_exceptionnels": 2444.31, "decaissements_total": 35371.27, "variation": 7678.73, "solde_cumule": 22378.73, "ligne_credit": 0, "creances_clients": 43648.46, "dettes_fournisseurs": 30553.92
      },
      {
        "month": 4, "periode": "Avr 2023", "year": 1, "monthInYear": 4, "ventes_mensuelles": 43954.43, "achats_mensuels": 15384.05, "encaissements_ventes": 43347, "encaissements_exceptionnels": 0, "encaissements_total": 43347, "decaissements_fournisseurs": 15384.05, "decaissements_salaires": 0, "decaissements_charges_fixes": 17650, "decaissements_exceptionnels": 0, "decaissements_total": 33034.05, "variation": 10312.95, "solde_cumule": 32691.68, "ligne_credit": 0, "creances_clients": 43954.43, "dettes_fournisseurs": 30768.1
      },
      {
        "month": 5, "periode": "Mai 2023", "year": 1, "monthInYear": 5, "ventes_mensuelles": 44265.0, "achats_mensuels": 15492.75, "encaissements_ventes": 43648.46, "encaissements_exceptionnels": 0, "encaissements_total": 43648.46, "decaissements_fournisseurs": 15492.75, "decaissements_salaires": 0, "decaissements_charges_fixes": 17650, "decaissements_exceptionnels": 0, "decaissements_total": 33142.75, "variation": 10505.71, "solde_cumule": 43197.38, "ligne_credit": 0, "creances_clients": 44265.0, "dettes_fournisseurs": 30985.5
      },
      {
        "month": 6, "periode": "Jun 2023", "year": 1, "monthInYear": 6, "ventes_mensuelles": 44580.22, "achats_mensuels": 15603.08, "encaissements_ventes": 43954.43, "encaissements_exceptionnels": 0, "encaissements_total": 43954.43, "decaissements_fournisseurs": 15603.08, "decaissements_salaires": 0, "decaissements_charges_fixes": 17650, "decaissements_exceptionnels": 2496.49, "decaissements_total": 35749.57, "variation": 8204.86, "solde_cumule": 51402.24, "ligne_credit": 0, "creances_clients": 44580.22, "dettes_fournisseurs": 31206.16
      },
      {
        "month": 7, "periode": "Jul 2023", "year": 1, "monthInYear": 7, "ventes_mensuelles": 114650.18, "achats_mensuels": 40127.56, "encaissements_ventes": 44265.0, "encaissements_exceptionnels": 0, "encaissements_total": 44265.0, "decaissements_fournisseurs": 40127.56, "decaissements_salaires": 0, "decaissements_charges_fixes": 17650, "decaissements_exceptionnels": 0, "decaissements_total": 57777.56, "variation": -13512.56, "solde_cumule": 37889.68, "ligne_credit": 0, "creances_clients": 114650.18, "dettes_fournisseurs": 80255.12
      },
      {
        "month": 8, "periode": "Aoû 2023", "year": 1, "monthInYear": 8, "ventes_mensuelles": 124974.93, "achats_mensuels": 43741.23, "encaissements_ventes": 44580.22, "encaissements_exceptionnels": 0, "encaissements_total": 44580.22, "decaissements_fournisseurs": 43741.23, "decaissements_salaires": 0, "decaissements_charges_fixes": 17650, "decaissements_exceptionnels": 0, "decaissements_total": 61391.23, "variation": -16811.0, "solde_cumule": 21078.68, "ligne_credit": 0, "creances_clients": 124974.93, "dettes_fournisseurs": 87482.45
      },
      {
        "month": 9, "periode": "Sep 2023", "year": 1, "monthInYear": 9, "ventes_mensuelles": 125604.55, "achats_mensuels": 43961.59, "encaissements_ventes": 114650.18, "encaissements_exceptionnels": 0, "encaissements_total": 114650.18, "decaissements_fournisseurs": 43961.59, "decaissements_salaires": 0, "decaissements_charges_fixes": 17650, "decaissements_exceptionnels": 7033.85, "decaissements_total": 68645.45, "variation": 46004.73, "solde_cumule": 67083.41, "ligne_credit": 0, "creances_clients": 125604.55, "dettes_fournisseurs": 87923.19
      },
      {
        "month": 10, "periode": "Oct 2023", "year": 1, "monthInYear": 10, "ventes_mensuelles": 126248.12, "achats_mensuels": 44186.84, "encaissements_ventes": 124974.93, "encaissements_exceptionnels": 0, "encaissements_total": 124974.93, "decaissements_fournisseurs": 44186.84, "decaissements_salaires": 0, "decaissements_charges_fixes": 17650, "decaissements_exceptionnels": 0, "decaissements_total": 61836.84, "variation": 63138.09, "solde_cumule": 130221.49, "ligne_credit": 0, "creances_clients": 126248.12, "dettes_fournisseurs": 88373.69
      },
      {
        "month": 11, "periode": "Nov 2023", "year": 1, "monthInYear": 11, "ventes_mensuelles": 126905.98, "achats_mensuels": 44417.09, "encaissements_ventes": 125604.55, "encaissements_exceptionnels": 0, "encaissements_total": 125604.55, "decaissements_fournisseurs": 44417.09, "decaissements_salaires": 0, "decaissements_charges_fixes": 17650, "decaissements_exceptionnels": 0, "decaissements_total": 62067.09, "variation": 63537.46, "solde_cumule": 193758.95, "ligne_credit": 0, "creances_clients": 126905.98, "dettes_fournisseurs": 88834.18
      },
      {
        "month": 12, "periode": "Déc 2023", "year": 1, "monthInYear": 12, "ventes_mensuelles": 127578.48, "achats_mensuels": 44652.47, "encaissements_ventes": 126248.12, "encaissements_exceptionnels": 0, "encaissements_total": 126248.12, "decaissements_fournisseurs": 44652.47, "decaissements_salaires": 0, "decaissements_charges_fixes": 17650, "decaissements_exceptionnels": 7144.39, "decaissements_total": 69446.86, "variation": 56801.26, "solde_cumule": 250560.21, "ligne_credit": 0, "creances_clients": 127578.48, "dettes_fournisseurs": 89304.93
      },
      {
        "month": 13, "periode": "Jan 2024", "year": 2, "monthInYear": 1, "ventes_mensuelles": 128265.98, "achats_mensuels": 44893.09, "encaissements_ventes": 126905.98, "encaissements_exceptionnels": 0, "encaissements_total": 126905.98, "decaissements_fournisseurs": 44893.09, "decaissements_salaires": 0, "decaissements_charges_fixes": 17650, "decaissements_exceptionnels": 0, "decaissements_total": 62543.09, "variation": 64362.89, "solde_cumule": 314923.1, "ligne_credit": 0, "creances_clients": 128265.98, "dettes_fournisseurs": 89786.19
      },
      {
        "month": 14, "periode": "Fév 2024", "year": 2, "monthInYear": 2, "ventes_mensuelles": 128968.86, "achats_mensuels": 45139.1, "encaissements_ventes": 127578.48, "encaissements_exceptionnels": 0, "encaissements_total": 127578.48, "decaissements_fournisseurs": 45139.1, "decaissements_salaires": 0, "decaissements_charges_fixes": 17650, "decaissements_exceptionnels": 0, "decaissements_total": 62789.1, "variation": 64789.38, "solde_cumule": 379712.47, "ligne_credit": 0, "creances_clients": 128968.86, "dettes_fournisseurs": 90278.2
      },
      {
        "month": 15, "periode": "Mar 2024", "year": 2, "monthInYear": 3, "ventes_mensuelles": 129687.5, "achats_mensuels": 45390.63, "encaissements_ventes": 128265.98, "encaissements_exceptionnels": 0, "encaissements_total": 128265.98, "decaissements_fournisseurs": 45390.63, "decaissements_salaires": 0, "decaissements_charges_fixes": 17650, "decaissements_exceptionnels": 7262.5, "decaissements_total": 70303.13, "variation": 57962.85, "solde_cumule": 437675.33, "ligne_credit": 0, "creances_clients": 129687.5, "dettes_fournisseurs": 90781.25
      },
      {
        "month": 16, "periode": "Avr 2024", "year": 2, "monthInYear": 4, "ventes_mensuelles": 130422.3, "achats_mensuels": 45647.8, "encaissements_ventes": 128968.86, "encaissements_exceptionnels": 0, "encaissements_total": 128968.86, "decaissements_fournisseurs": 45647.8, "decaissements_salaires": 0, "decaissements_charges_fixes": 17650, "decaissements_exceptionnels": 0, "decaissements_total": 63297.8, "variation": 65671.06, "solde_cumule": 503346.39, "ligne_credit": 0, "creances_clients": 130422.3, "dettes_fournisseurs": 91295.61
      },
      {
        "month": 17, "periode": "Mai 2024", "year": 2, "monthInYear": 5, "ventes_mensuelles": 131173.65, "achats_mensuels": 45910.78, "encaissements_ventes": 129687.5, "encaissements_exceptionnels": 0, "encaissements_total": 129687.5, "decaissements_fournisseurs": 45910.78, "decaissements_salaires": 0, "decaissements_charges_fixes": 17650, "decaissements_exceptionnels": 0, "decaissements_total": 63560.78, "variation": 66126.73, "solde_cumule": 569473.11, "ligne_credit": 0, "creances_clients": 131173.65, "dettes_fournisseurs": 91821.55
      },
      {
        "month": 18, "periode": "Jun 2024", "year": 2, "monthInYear": 6, "ventes_mensuelles": 131941.97, "achats_mensuels": 46179.69, "encaissements_ventes": 130422.3, "encaissements_exceptionnels": 0, "encaissements_total": 130422.3, "decaissements_fournisseurs": 46179.69, "decaissements_salaires": 0, "decaissements_charges_fixes": 17650, "decaissements_exceptionnels": 7388.75, "decaissements_total": 71218.44, "variation": 59203.86, "solde_cumule": 628676.97, "ligne_credit": 0, "creances_clients": 131941.97, "dettes_fournisseurs": 92359.38
      },
      {
        "month": 19, "periode": "Jul 2024", "year": 2, "monthInYear": 7, "ventes_mensuelles": 132727.68, "achats_mensuels": 46454.69, "encaissements_ventes": 131173.65, "encaissements_exceptionnels": 0, "encaissements_total": 131173.65, "decaissements_fournisseurs": 46454.69, "decaissements_salaires": 0, "decaissements_charges_fixes": 17650, "decaissements_exceptionnels": 0, "decaissements_total": 64104.69, "variation": 67068.96, "solde_cumule": 695745.93, "ligne_credit": 0, "creances_clients": 132727.68, "dettes_fournisseurs": 92909.38
      },
      {
        "month": 20, "periode": "Aoû 2024", "year": 2, "monthInYear": 8, "ventes_mensuelles": 133531.23, "achats_mensuels": 46735.93, "encaissements_ventes": 131941.97, "encaissements_exceptionnels": 0, "encaissements_total": 131941.97, "decaissements_fournisseurs": 46735.93, "decaissements_salaires": 0, "decaissements_charges_fixes": 17650, "decaissements_exceptionnels": 0, "decaissements_total": 64385.93, "variation": 67556.03, "solde_cumule": 763301.96, "ligne_credit": 0, "creances_clients": 133531.23, "dettes_fournisseurs": 93471.86
      },
      {
        "month": 21, "periode": "Sep 2024", "year": 2, "monthInYear": 9, "ventes_mensuelles": 160603.07, "achats_mensuels": 56211.07, "encaissements_ventes": 132727.68, "encaissements_exceptionnels": 0, "encaissements_total": 132727.68, "decaissements_fournisseurs": 56211.07, "decaissements_salaires": 0, "decaissements_charges_fixes": 17650, "decaissements_exceptionnels": 8993.77, "decaissements_total": 82854.84, "variation": 49872.84, "solde_cumule": 813174.8, "ligne_credit": 0, "creances_clients": 160603.07, "dettes_fournisseurs": 112422.15
      },
      {
        "month": 22, "periode": "Oct 2024", "year": 2, "monthInYear": 10, "ventes_mensuelles": 161443.64, "achats_mensuels": 56505.27, "encaissements_ventes": 133531.23, "encaissements_exceptionnels": 0, "encaissements_total": 133531.23, "decaissements_fournisseurs": 56505.27, "decaissements_salaires": 0, "decaissements_charges_fixes": 17650, "decaissements_exceptionnels": 0, "decaissements_total": 74155.27, "variation": 59375.96, "solde_cumule": 872550.76, "ligne_credit": 0, "creances_clients": 161443.64, "dettes_fournisseurs": 113010.55
      },
      {
        "month": 23, "periode": "Nov 2024", "year": 2, "monthInYear": 11, "ventes_mensuelles": 162303.44, "achats_mensuels": 56806.2, "encaissements_ventes": 160603.07, "encaissements_exceptionnels": 0, "encaissements_total": 160603.07, "decaissements_fournisseurs": 56806.2, "decaissements_salaires": 0, "decaissements_charges_fixes": 17650, "decaissements_exceptionnels": 0, "decaissements_total": 74456.2, "variation": 86146.86, "solde_cumule": 958697.62, "ligne_credit": 0, "creances_clients": 162303.44, "dettes_fournisseurs": 113612.4
      },
      {
        "month": 24, "periode": "Déc 2024", "year": 2, "monthInYear": 12, "ventes_mensuelles": 163182.93, "achats_mensuels": 57114.03, "encaissements_ventes": 161443.64, "encaissements_exceptionnels": 0, "encaissements_total": 161443.64, "decaissements_fournisseurs": 57114.03, "decaissements_salaires": 0, "decaissements_charges_fixes": 17650, "decaissements_exceptionnels": 9138.24, "decaissements_total": 83902.27, "variation": 77541.37, "solde_cumule": 1036238.99, "ligne_credit": 0, "creances_clients": 163182.93, "dettes_fournisseurs": 114228.05
      },
      {
        "month": 25, "periode": "Jan 2025", "year": 3, "monthInYear": 1, "ventes_mensuelles": 164082.63, "achats_mensuels": 57428.92, "encaissements_ventes": 162303.44, "encaissements_exceptionnels": 0, "encaissements_total": 162303.44, "decaissements_fournisseurs": 57428.92, "decaissements_salaires": 0, "decaissements_charges_fixes": 17650, "decaissements_exceptionnels": 0, "decaissements_total": 75078.92, "variation": 87224.51, "solde_cumule": 1123463.51, "ligne_credit": 0, "creances_clients": 164082.63, "dettes_fournisseurs": 114857.84
      },
      {
        "month": 26, "periode": "Fév 2025", "year": 3, "monthInYear": 2, "ventes_mensuelles": 165003.05, "achats_mensuels": 57751.07, "encaissements_ventes": 163182.93, "encaissements_exceptionnels": 0, "encaissements_total": 163182.93, "decaissements_fournisseurs": 57751.07, "decaissements_salaires": 0, "decaissements_charges_fixes": 17650, "decaissements_exceptionnels": 0, "decaissements_total": 75401.07, "variation": 87781.87, "solde_cumule": 1211245.37, "ligne_credit": 0, "creances_clients": 165003.05, "dettes_fournisseurs": 115502.13
      },
      {
        "month": 27, "periode": "Mar 2025", "year": 3, "monthInYear": 3, "ventes_mensuelles": 165944.71, "achats_mensuels": 58080.65, "encaissements_ventes": 164082.63, "encaissements_exceptionnels": 0, "encaissements_total": 164082.63, "decaissements_fournisseurs": 58080.65, "decaissements_salaires": 0, "decaissements_charges_fixes": 17650, "decaissements_exceptionnels": 9292.9, "decaissements_total": 85023.55, "variation": 79059.08, "solde_cumule": 1290304.45, "ligne_credit": 0, "creances_clients": 165944.71, "dettes_fournisseurs": 116161.3
      },
      {
        "month": 28, "periode": "Avr 2025", "year": 3, "monthInYear": 4, "ventes_mensuelles": 166908.16, "achats_mensuels": 58417.85, "encaissements_ventes": 165003.05, "encaissements_exceptionnels": 0, "encaissements_total": 165003.05, "decaissements_fournisseurs": 58417.85, "decaissements_salaires": 0, "decaissements_charges_fixes": 17650, "decaissements_exceptionnels": 0, "decaissements_total": 76067.85, "variation": 88935.19, "solde_cumule": 1379239.65, "ligne_credit": 0, "creances_clients": 166908.16, "dettes_fournisseurs": 116835.71
      },
      {
        "month": 29, "periode": "Mai 2025", "year": 3, "monthInYear": 5, "ventes_mensuelles": 167893.94, "achats_mensuels": 58762.88, "encaissements_ventes": 165944.71, "encaissements_exceptionnels": 0, "encaissements_total": 165944.71, "decaissements_fournisseurs": 58762.88, "decaissements_salaires": 0, "decaissements_charges_fixes": 17650, "decaissements_exceptionnels": 0, "decaissements_total": 76412.88, "variation": 89531.83, "solde_cumule": 1468771.48, "ligne_credit": 0, "creances_clients": 167893.94, "dettes_fournisseurs": 117525.76
      },
      {
        "month": 30, "periode": "Jun 2025", "year": 3, "monthInYear": 6, "ventes_mensuelles": 168902.65, "achats_mensuels": 59115.93, "encaissements_ventes": 166908.16, "encaissements_exceptionnels": 0, "encaissements_total": 166908.16, "decaissements_fournisseurs": 59115.93, "decaissements_salaires": 0, "decaissements_charges_fixes": 17650, "decaissements_exceptionnels": 9458.55, "decaissements_total": 86224.48, "variation": 80683.68, "solde_cumule": 1549455.16, "ligne_credit": 0, "creances_clients": 168902.65, "dettes_fournisseurs": 118231.85
      },
      {
        "month": 31, "periode": "Jul 2025", "year": 3, "monthInYear": 7, "ventes_mensuelles": 169934.85, "achats_mensuels": 59477.2, "encaissements_ventes": 167893.94, "encaissements_exceptionnels": 0, "encaissements_total": 167893.94, "decaissements_fournisseurs": 59477.2, "decaissements_salaires": 0, "decaissements_charges_fixes": 17650, "decaissements_exceptionnels": 0, "decaissements_total": 77127.2, "variation": 90766.75, "solde_cumule": 1640221.9, "ligne_credit": 0, "creances_clients": 169934.85, "dettes_fournisseurs": 118954.4
      },
      {
        "month": 32, "periode": "Aoû 2025", "year": 3, "monthInYear": 8, "ventes_mensuelles": 170991.16, "achats_mensuels": 59846.91, "encaissements_ventes": 168902.65, "encaissements_exceptionnels": 0, "encaissements_total": 168902.65, "decaissements_fournisseurs": 59846.91, "decaissements_salaires": 0, "decaissements_charges_fixes": 17650, "decaissements_exceptionnels": 0, "decaissements_total": 77496.91, "variation": 91405.74, "solde_cumule": 1731627.64, "ligne_credit": 0, "creances_clients": 170991.16, "dettes_fournisseurs": 119693.81
      },
      {
        "month": 33, "periode": "Sep 2025", "year": 3, "monthInYear": 9, "ventes_mensuelles": 172072.2, "achats_mensuels": 60225.27, "encaissements_ventes": 169934.85, "encaissements_exceptionnels": 0, "encaissements_total": 169934.85, "decaissements_fournisseurs": 60225.27, "decaissements_salaires": 0, "decaissements_charges_fixes": 17650, "decaissements_exceptionnels": 9636.04, "decaissements_total": 87511.31, "variation": 82423.54, "solde_cumule": 1814051.18, "ligne_credit": 0, "creances_clients": 172072.2, "dettes_fournisseurs": 120450.54
      },
      {
        "month": 34, "periode": "Oct 2025", "year": 3, "monthInYear": 10, "ventes_mensuelles": 173178.6, "achats_mensuels": 60612.51, "encaissements_ventes": 170991.16, "encaissements_exceptionnels": 0, "encaissements_total": 170991.16, "decaissements_fournisseurs": 60612.51, "decaissements_salaires": 0, "decaissements_charges_fixes": 17650, "decaissements_exceptionnels": 0, "decaissements_total": 78262.51, "variation": 92728.65, "solde_cumule": 1906779.84, "ligne_credit": 0, "creances_clients": 173178.6, "dettes_fournisseurs": 121225.02
      },
      {
        "month": 35, "periode": "Nov 2025", "year": 3, "monthInYear": 11, "ventes_mensuelles": 174311.02, "achats_mensuels": 61008.86, "encaissements_ventes": 172072.2, "encaissements_exceptionnels": 0, "encaissements_total": 172072.2, "decaissements_fournisseurs": 61008.86, "decaissements_salaires": 0, "decaissements_charges_fixes": 17650, "decaissements_exceptionnels": 0, "decaissements_total": 78658.86, "variation": 93413.34, "solde_cumule": 2000193.18, "ligne_credit": 0, "creances_clients": 174311.02, "dettes_fournisseurs": 122017.71
      },
      {
        "month": 36, "periode": "Déc 2025", "year": 3, "monthInYear": 12, "ventes_mensuelles": 175470.13, "achats_mensuels": 61414.54, "encaissements_ventes": 173178.6, "encaissements_exceptionnels": 0, "encaissements_total": 173178.6, "decaissements_fournisseurs": 61414.54, "decaissements_salaires": 0, "decaissements_charges_fixes": 17650, "decaissements_exceptionnels": 9826.33, "decaissements_total": 88890.87, "variation": 84287.73, "solde_cumule": 2084480.91, "ligne_credit": 0, "creances_clients": 175470.13, "dettes_fournisseurs": 122829.09
      }
    ],
    "treasuryIndicators": {
      "pointBas": 14700, "moisPointBas": 2, "moisRetourPositif": 2, "soldeFinal": 2084480.91, "ligneCreditMax": 0
    },
    "incomeStatement": [
        {
          "year": 1, "chiffre_affaires": 1220000, "production_stockee": 15000, "production_immobilisee": 0, "production_totale": 1235000, "consommations_matieres": 361000, "autres_achats": 61000, "charges_externes": null, "charges_externes_detail": {"sous_traitance": 24400, "locations": 54000, "maintenance": null, "assurances": null, "autres_services": 36600, "transport": 18300, "frais_postaux": 2400, "services_bancaires": null, "publicite": null, "formation": null}, "valeur_ajoutee": null, "salaires_bruts": 0, "charges_sociales": 0, "autres_charges_personnel": 0, "charges_personnel": 0, "impots_taxes": {"taxe_professionnelle": 1220, "taxe_fonciere": null, "autres_impots": 3000}, "total_impots_taxes": null, "ebe": null, "autres_produits_exploitation": 1220, "autres_charges_exploitation": 2440, "amortissements": null, "resultat_exploitation": null, "produits_financiers": 500, "charges_financieres": 30000, "resultat_financier": -29500, "resultat_courant": null, "produits_exceptionnels": 0, "charges_exceptionnelles": 5000, "resultat_exceptionnel": -5000, "participation_salaries": null, "impot_benefices": null, "resultat_net": null, "caf": null
        },
        {
          "year": 2, "chiffre_affaires": 1897000, "production_stockee": 25000, "production_immobilisee": 0, "production_totale": 1922000, "consommations_matieres": 561100, "autres_achats": 94850, "charges_externes": null, "charges_externes_detail": {"sous_traitance": 37940, "locations": 54000, "maintenance": null, "assurances": null, "autres_services": 56910, "transport": 28455, "frais_postaux": 2400, "services_bancaires": null, "publicite": null, "formation": null}, "valeur_ajoutee": null, "salaires_bruts": 0, "charges_sociales": 0, "autres_charges_personnel": 0, "charges_personnel": 0, "impots_taxes": {"taxe_professionnelle": 1897, "taxe_fonciere": null, "autres_impots": 3000}, "total_impots_taxes": null, "ebe": null, "autres_produits_exploitation": 1897, "autres_charges_exploitation": 3794, "amortissements": null, "resultat_exploitation": null, "produits_financiers": 1200, "charges_financieres": 25000, "resultat_financier": -23800, "resultat_courant": null, "produits_exceptionnels": 0, "charges_exceptionnelles": 0, "resultat_exceptionnel": 0, "participation_salaries": null, "impot_benefices": null, "resultat_net": null, "caf": null
        },
        {
          "year": 3, "chiffre_affaires": 2986000, "production_stockee": 35000, "production_immobilisee": 0, "production_totale": 3021000, "consommations_matieres": 883800, "autres_achats": 149300, "charges_externes": null, "charges_externes_detail": {"sous_traitance": 59720, "locations": 54000, "maintenance": null, "assurances": null, "autres_services": 89580, "transport": 44790, "frais_postaux": 2400, "services_bancaires": null, "publicite": null, "formation": null}, "valeur_ajoutee": null, "salaires_bruts": 0, "charges_sociales": 0, "autres_charges_personnel": 0, "charges_personnel": 0, "impots_taxes": {"taxe_professionnelle": 2986, "taxe_fonciere": null, "autres_impots": 3000}, "total_impots_taxes": null, "ebe": null, "autres_produits_exploitation": 2986, "autres_charges_exploitation": 5972, "amortissements": null, "resultat_exploitation": null, "produits_financiers": 2500, "charges_financieres": 20000, "resultat_financier": -17500, "resultat_courant": null, "produits_exceptionnels": 0, "charges_exceptionnelles": 0, "resultat_exceptionnel": 0, "participation_salaries": null, "impot_benefices": null, "resultat_net": null, "caf": null
        }
    ],
    "irr": null
  }
}
